setup.cfg
setup.py
pwm/__init__.py
pwm/_compat.py
pwm/cli.py
pwm/core.py
pwm/encoding.py
pwm/exceptions.py
pwm.egg-info/PKG-INFO
pwm.egg-info/SOURCES.txt
pwm.egg-info/dependency_links.txt
pwm.egg-info/entry_points.txt
pwm.egg-info/requires.txt
pwm.egg-info/top_level.txt