Metadata-Version: 1.1
Name: pwm
Version: 0.1.3
Summary: A superlight password manager
Home-page: https://github.com/thusoy/pwm
Author: Tarjei Husøy
Author-email: tarjei@roms.no
License: UNKNOWN
Platform: UNKNOWN
Classifier: Development Status :: 2 - Pre-Alpha
Classifier: Intended Audience :: Developers
Classifier: Intended Audience :: End Users/Desktop
Classifier: License :: OSI Approved :: MIT License
Classifier: Programming Language :: Python :: 2.6
Classifier: Programming Language :: Python :: 2.7
Classifier: Programming Language :: Python :: 3.3
